ALU/halfadder.v
module HALFADDER(C, S, A, B);
    output C, S;
    input A, B;

    and G1 (C, A, B);
    xor G2 (S, A, B);

endmodule

ALU/fulladder.v
module FULLADDER(Carry, Sum, IN1, IN2, IN3);
    output Carry, Sum;
    input IN1, IN2, IN3;
    wire T1, T2, T3;

    // For Sum
    HALFADDER G1(T2, T1, IN1, IN2);
    HALFADDER G2(T3, Sum, T1, IN3);

    // For Carry
    xor G3(Carry, T2, T3);

endmodule

ALU/fulladder_tb.v
module t_FULLADDER;
    wire [1:0]OUT;
    reg [2:0]IN;

    FULLADDER fadd(OUT[1], OUT[0], IN[2], IN[1], IN[0]);

    initial
        begin
            $dumpfile("fulladder.vcd");
            $dumpvars(0, fadd);
            $monitor("Time: %d -> A: %b, B: %b, C: %b | Carry: %b, Sum: %b", $time, IN[2], IN[1], IN[0], OUT[1], OUT[0]);
            IN = 3'b000;
            repeat(7) #10 IN = IN + 1'b1;
            #10 $finish;
        end

endmodule

ALU/fulladder.vcd
$date
	Sun Aug 22 15:18:34 2021
$end
$version
	Icarus Verilog
$end
$timescale
	1s
$end
$scope module t_FULLADDER $end
$scope module fadd $end
$var wire 1 ! Carry $end
$var wire 1 " IN1 $end
$var wire 1 # IN2 $end
$var wire 1 $ IN3 $end
$var wire 1 % T3 $end
$var wire 1 & T2 $end
$var wire 1 ' T1 $end
$var wire 1 ( Sum $end
$scope module G1 $end
$var wire 1 " A $end
$var wire 1 # B $end
$var wire 1 & C $end
$var wire 1 ' S $end
$upscope $end
$scope module G2 $end
$var wire 1 ' A $end
$var wire 1 $ B $end
$var wire 1 % C $end
$var wire 1 ( S $end
$upscope $end
$upscope $end
$upscope $end
$enddefinitions $end
#0
$dumpvars
0(
0'
0&
0%
0$
0#
0"
0!
$end
#10
1(
1$
#20
1'
1(
1#
0$
#30
1!
1%
0(
1$
#40
0!
0%
1(
1"
0#
0$
#50
1!
1%
0(
1$
#60
1&
0'
0%
0(
1#
0$
#70
1(
1$
