BasicGates/not.v
module NOT(A_b, A);
    output A_b;
    input A;

    nand G1(A_b, A);

endmodule

BasicGates/and.v
module AND(C, A, B);
    output C;
    input A, B;
    wire C_b;

    nand G1(C_b, A, B);
    NOT G2(C, C_b);

endmodule

BasicGates/demux1x2.v
module DEMUX1x2(A, B, I, S);
    output A, B;
    input I, S;
    wire S_b;

    NOT G1(S_b, S);
    AND G2(A, S_b, I);
    AND G3(B, S, I);

endmodule

BasicGates/demux1x4.v
module DEMUX1x4(OUT, IN, SEL);
    output [3:0]OUT;
    input [1:0]SEL;
    input IN;
    wire T0, T1;
    
    DEMUX1x2 G1(T0, T1, IN, SEL[1]);
    DEMUX1x2 G2(OUT[0], OUT[1], T0, SEL[0]);
    DEMUX1x2 G3(OUT[2], OUT[3], T1, SEL[0]);

endmodule

BasicGates/demux1x4_tb.v
module t_DEMUX1x4;
    wire [3:0]OUT;
    reg [2:0]IN;

    DEMUX1x4 demux2(OUT, IN[2], IN[1:0]);

    initial
        begin
            $dumpfile("demux1x4.vcd");
            $dumpvars(0, demux2);
            $monitor("Time: %d, IN: %b, S: %b, OUT: %b", $time, IN[2], IN[1:0], OUT);
            IN = 3'b000;
            repeat(7) #10 IN = IN + 1'b1;
            #10 $finish;
        end

endmodule

BasicGates/demux1x4.vcd
$date
	Fri Aug 20 19:40:06 2021
$end
$version
	Icarus Verilog
$end
$timescale
	1s
$end
$scope module t_DEMUX1x4 $end
$scope module demux2 $end
$var wire 1 ! IN $end
$var wire 2 " SEL [1:0] $end
$var wire 1 # T1 $end
$var wire 1 $ T0 $end
$var wire 4 % OUT [3:0] $end
$scope module G1 $end
$var wire 1 ! I $end
$var wire 1 & S $end
$var wire 1 ' S_b $end
$var wire 1 # B $end
$var wire 1 $ A $end
$scope module G1 $end
$var wire 1 & A $end
$var wire 1 ' A_b $end
$upscope $end
$scope module G2 $end
$var wire 1 ' A $end
$var wire 1 ! B $end
$var wire 1 ( C_b $end
$var wire 1 $ C $end
$scope module G2 $end
$var wire 1 ( A $end
$var wire 1 $ A_b $end
$upscope $end
$upscope $end
$scope module G3 $end
$var wire 1 & A $end
$var wire 1 ! B $end
$var wire 1 ) C_b $end
$var wire 1 # C $end
$scope module G2 $end
$var wire 1 ) A $end
$var wire 1 # A_b $end
$upscope $end
$upscope $end
$upscope $end
$scope module G2 $end
$var wire 1 $ I $end
$var wire 1 * S $end
$var wire 1 + S_b $end
$var wire 1 , B $end
$var wire 1 - A $end
$scope module G1 $end
$var wire 1 * A $end
$var wire 1 + A_b $end
$upscope $end
$scope module G2 $end
$var wire 1 + A $end
$var wire 1 $ B $end
$var wire 1 . C_b $end
$var wire 1 - C $end
$scope module G2 $end
$var wire 1 . A $end
$var wire 1 - A_b $end
$upscope $end
$upscope $end
$scope module G3 $end
$var wire 1 * A $end
$var wire 1 $ B $end
$var wire 1 / C_b $end
$var wire 1 , C $end
$scope module G2 $end
$var wire 1 / A $end
$var wire 1 , A_b $end
$upscope $end
$upscope $end
$upscope $end
$scope module G3 $end
$var wire 1 # I $end
$var wire 1 0 S $end
$var wire 1 1 S_b $end
$var wire 1 2 B $end
$var wire 1 3 A $end
$scope module G1 $end
$var wire 1 0 A $end
$var wire 1 1 A_b $end
$upscope $end
$scope module G2 $end
$var wire 1 1 A $end
$var wire 1 # B $end
$var wire 1 4 C_b $end
$var wire 1 3 C $end
$scope module G2 $end
$var wire 1 4 A $end
$var wire 1 3 A_b $end
$upscope $end
$upscope $end
$scope module G3 $end
$var wire 1 0 A $end
$var wire 1 # B $end
$var wire 1 5 C_b $end
$var wire 1 2 C $end
$scope module G2 $end
$var wire 1 5 A $end
$var wire 1 2 A_b $end
$upscope $end
$upscope $end
$upscope $end
$upscope $end
$upscope $end
$enddefinitions $end
#0
$dumpvars
15
14
03
02
11
00
1/
1.
0-
0,
1+
0*
1)
1(
1'
0&
b0 %
0$
0#
b0 "
0!
$end
#10
0+
01
1*
10
b1 "
#20
0'
1+
11
1&
0*
00
b10 "
#30
0+
01
1*
10
b11 "
#40
b1 %
1-
0.
1$
0(
1'
1+
11
0&
0*
00
1!
b0 "
#50
0-
1.
b10 %
1,
0+
0/
01
1*
10
b1 "
#60
13
0$
04
0-
1(
1#
1.
b100 %
0,
0'
0)
1+
1/
11
1&
0*
00
b10 "
#70
03
14
b1000 %
12
0+
01
05
1*
10
b11 "
