BasicGates/not.v
module NOT(A_b, A);
    output A_b;
    input A;

    nand G1(A_b, A);

endmodule

BasicGates/and.v
module AND(C, A, B);
    output C;
    input A, B;
    wire C_b;

    nand G1(C_b, A, B);
    NOT G2(C, C_b);

endmodule

BasicGates/or.v
module OR(C, A, B);
    output C;
    input A, B;
    wire A_b, B_b, AB_b;

    NOT G1(A_b, A);
    NOT G2(B_b, B);
    AND G3(AB_b, A_b, B_b);
    NOT G4(C, AB_b);

endmodule

BasicGates/mux2x1.v
module MUX2x1(O, A, B, S);
    output O;
    input A, B, S;
    wire S_b, T1, T2;

    NOT G1(S_b, S);
    AND G2(T1, S_b, A);
    AND G3(T2, S, B);
    OR G4(O, T1, T2);

endmodule

BasicGates/mux2x1_tb.v
module t_MUX2x1;
    reg [2:0]A;
    wire B;

    MUX2x1 mux1(B, A[2], A[1], A[0]);

    initial
        begin
            $dumpfile("mux2x1.vcd");
            $dumpvars(0, mux1);
            $monitor("Time: %d, A: %b, B: %b, S: %b, O: %b", $time, A[2], A[1], A[0], B);
            A = 3'b000;
            repeat(7) #10 A = A + 1'b1;
            #10 $finish;
        end

endmodule

BasicGates/mux2x1.vcd
$date
	Thu Aug 19 19:32:27 2021
$end
$version
	Icarus Verilog
$end
$timescale
	1s
$end
$scope module t_MUX2x1 $end
$scope module mux1 $end
$var wire 1 ! A $end
$var wire 1 " B $end
$var wire 1 # S $end
$var wire 1 $ T2 $end
$var wire 1 % T1 $end
$var wire 1 & S_b $end
$var wire 1 ' O $end
$scope module G1 $end
$var wire 1 # A $end
$var wire 1 & A_b $end
$upscope $end
$scope module G2 $end
$var wire 1 & A $end
$var wire 1 ! B $end
$var wire 1 ( C_b $end
$var wire 1 % C $end
$scope module G2 $end
$var wire 1 ( A $end
$var wire 1 % A_b $end
$upscope $end
$upscope $end
$scope module G3 $end
$var wire 1 # A $end
$var wire 1 " B $end
$var wire 1 ) C_b $end
$var wire 1 $ C $end
$scope module G2 $end
$var wire 1 ) A $end
$var wire 1 $ A_b $end
$upscope $end
$upscope $end
$scope module G4 $end
$var wire 1 % A $end
$var wire 1 $ B $end
$var wire 1 ' C $end
$var wire 1 * B_b $end
$var wire 1 + A_b $end
$var wire 1 , AB_b $end
$scope module G1 $end
$var wire 1 % A $end
$var wire 1 + A_b $end
$upscope $end
$scope module G2 $end
$var wire 1 $ A $end
$var wire 1 * A_b $end
$upscope $end
$scope module G3 $end
$var wire 1 + A $end
$var wire 1 * B $end
$var wire 1 - C_b $end
$var wire 1 , C $end
$scope module G2 $end
$var wire 1 - A $end
$var wire 1 , A_b $end
$upscope $end
$upscope $end
$scope module G4 $end
$var wire 1 , A $end
$var wire 1 ' A_b $end
$upscope $end
$upscope $end
$upscope $end
$upscope $end
$enddefinitions $end
#0
$dumpvars
0-
1,
1+
1*
1)
1(
0'
1&
0%
0$
0#
0"
0!
$end
#10
0&
1#
#20
1&
1"
0#
#30
1'
0,
1-
0*
1$
0&
0)
1#
#40
0+
1*
1%
0$
0(
1&
1)
1!
0"
0#
#50
0'
1,
0-
1+
0%
1(
0&
1#
#60
1'
0,
1-
0+
1%
0(
1&
1"
0#
#70
1+
0%
0*
1(
1$
0&
0)
1#
