BasicGates/not.v
module NOT(A_b, A);
    output A_b;
    input A;

    nand G1(A_b, A);

endmodule

BasicGates/and.v
module AND(C, A, B);
    output C;
    input A, B;
    wire C_b;

    nand G1(C_b, A, B);
    NOT G2(C, C_b);

endmodule

BasicGates/or.v
module OR(C, A, B);
    output C;
    input A, B;
    wire A_b, B_b, AB_b;

    NOT G1(A_b, A);
    NOT G2(B_b, B);
    AND G3(AB_b, A_b, B_b);
    NOT G4(C, AB_b);

endmodule

BasicGates/mux2x1.v
module MUX2x1(O, A, B, S);
    output O;
    input A, B, S;
    wire S_b, T1, T2;

    NOT G1(S_b, S);
    AND G2(T1, S_b, A);
    AND G3(T2, S, B);
    OR G4(O, T1, T2);

endmodule

BasicGates/mux4x1.v
module MUX4x1(O, I0, I1, I2, I3, S0, S1);
    output O;
    input I0, I1, I2, I3, S0, S1;
    wire T1, T2;

    MUX2x1 G1(T1, I3, I2, S1);
    MUX2x1 G2(T2, I1, I0, S1);
    MUX2x1 G3(O, T1, T2, S0);

endmodule

BasicGates/mux4x1_tb.v
module t_MUX4x1;
    wire O;
    reg [5:0]I;

    MUX4x1 mux2(O, I[3], I[2], I[1], I[0], I[5], I[4]);

    initial
        begin
            $dumpfile("mux4x1.vcd");
            $dumpvars(0, mux2);
            $monitor("Time: %d, I: %b, S: %b, O: %b", $time, I[3:0], I[5:4], O);
            I = 6'b000000;
            repeat(63) #10 I = I + 1'b1;
            #10 $finish;
        end

endmodule

BasicGates/mux4x1.vcd
$date
	Fri Aug 20 14:53:32 2021
$end
$version
	Icarus Verilog
$end
$timescale
	1s
$end
$scope module t_MUX4x1 $end
$scope module mux2 $end
$var wire 1 ! I0 $end
$var wire 1 " I1 $end
$var wire 1 # I2 $end
$var wire 1 $ I3 $end
$var wire 1 % S0 $end
$var wire 1 & S1 $end
$var wire 1 ' T2 $end
$var wire 1 ( T1 $end
$var wire 1 ) O $end
$scope module G1 $end
$var wire 1 $ A $end
$var wire 1 # B $end
$var wire 1 & S $end
$var wire 1 * T2 $end
$var wire 1 + T1 $end
$var wire 1 , S_b $end
$var wire 1 ( O $end
$scope module G1 $end
$var wire 1 & A $end
$var wire 1 , A_b $end
$upscope $end
$scope module G2 $end
$var wire 1 , A $end
$var wire 1 $ B $end
$var wire 1 - C_b $end
$var wire 1 + C $end
$scope module G2 $end
$var wire 1 - A $end
$var wire 1 + A_b $end
$upscope $end
$upscope $end
$scope module G3 $end
$var wire 1 & A $end
$var wire 1 # B $end
$var wire 1 . C_b $end
$var wire 1 * C $end
$scope module G2 $end
$var wire 1 . A $end
$var wire 1 * A_b $end
$upscope $end
$upscope $end
$scope module G4 $end
$var wire 1 + A $end
$var wire 1 * B $end
$var wire 1 ( C $end
$var wire 1 / B_b $end
$var wire 1 0 A_b $end
$var wire 1 1 AB_b $end
$scope module G1 $end
$var wire 1 + A $end
$var wire 1 0 A_b $end
$upscope $end
$scope module G2 $end
$var wire 1 * A $end
$var wire 1 / A_b $end
$upscope $end
$scope module G3 $end
$var wire 1 0 A $end
$var wire 1 / B $end
$var wire 1 2 C_b $end
$var wire 1 1 C $end
$scope module G2 $end
$var wire 1 2 A $end
$var wire 1 1 A_b $end
$upscope $end
$upscope $end
$scope module G4 $end
$var wire 1 1 A $end
$var wire 1 ( A_b $end
$upscope $end
$upscope $end
$upscope $end
$scope module G2 $end
$var wire 1 " A $end
$var wire 1 ! B $end
$var wire 1 & S $end
$var wire 1 3 T2 $end
$var wire 1 4 T1 $end
$var wire 1 5 S_b $end
$var wire 1 ' O $end
$scope module G1 $end
$var wire 1 & A $end
$var wire 1 5 A_b $end
$upscope $end
$scope module G2 $end
$var wire 1 5 A $end
$var wire 1 " B $end
$var wire 1 6 C_b $end
$var wire 1 4 C $end
$scope module G2 $end
$var wire 1 6 A $end
$var wire 1 4 A_b $end
$upscope $end
$upscope $end
$scope module G3 $end
$var wire 1 & A $end
$var wire 1 ! B $end
$var wire 1 7 C_b $end
$var wire 1 3 C $end
$scope module G2 $end
$var wire 1 7 A $end
$var wire 1 3 A_b $end
$upscope $end
$upscope $end
$scope module G4 $end
$var wire 1 4 A $end
$var wire 1 3 B $end
$var wire 1 ' C $end
$var wire 1 8 B_b $end
$var wire 1 9 A_b $end
$var wire 1 : AB_b $end
$scope module G1 $end
$var wire 1 4 A $end
$var wire 1 9 A_b $end
$upscope $end
$scope module G2 $end
$var wire 1 3 A $end
$var wire 1 8 A_b $end
$upscope $end
$scope module G3 $end
$var wire 1 9 A $end
$var wire 1 8 B $end
$var wire 1 ; C_b $end
$var wire 1 : C $end
$scope module G2 $end
$var wire 1 ; A $end
$var wire 1 : A_b $end
$upscope $end
$upscope $end
$scope module G4 $end
$var wire 1 : A $end
$var wire 1 ' A_b $end
$upscope $end
$upscope $end
$upscope $end
$scope module G3 $end
$var wire 1 ( A $end
$var wire 1 ' B $end
$var wire 1 % S $end
$var wire 1 < T2 $end
$var wire 1 = T1 $end
$var wire 1 > S_b $end
$var wire 1 ) O $end
$scope module G1 $end
$var wire 1 % A $end
$var wire 1 > A_b $end
$upscope $end
$scope module G2 $end
$var wire 1 > A $end
$var wire 1 ( B $end
$var wire 1 ? C_b $end
$var wire 1 = C $end
$scope module G2 $end
$var wire 1 ? A $end
$var wire 1 = A_b $end
$upscope $end
$upscope $end
$scope module G3 $end
$var wire 1 % A $end
$var wire 1 ' B $end
$var wire 1 @ C_b $end
$var wire 1 < C $end
$scope module G2 $end
$var wire 1 @ A $end
$var wire 1 < A_b $end
$upscope $end
$upscope $end
$scope module G4 $end
$var wire 1 = A $end
$var wire 1 < B $end
$var wire 1 ) C $end
$var wire 1 A B_b $end
$var wire 1 B A_b $end
$var wire 1 C AB_b $end
$scope module G1 $end
$var wire 1 = A $end
$var wire 1 B A_b $end
$upscope $end
$scope module G2 $end
$var wire 1 < A $end
$var wire 1 A A_b $end
$upscope $end
$scope module G3 $end
$var wire 1 B A $end
$var wire 1 A B $end
$var wire 1 D C_b $end
$var wire 1 C C $end
$scope module G2 $end
$var wire 1 D A $end
$var wire 1 C A_b $end
$upscope $end
$upscope $end
$scope module G4 $end
$var wire 1 C A $end
$var wire 1 ) A_b $end
$upscope $end
$upscope $end
$upscope $end
$upscope $end
$upscope $end
$enddefinitions $end
#0
$dumpvars
0D
1C
1B
1A
1@
1?
1>
0=
0<
0;
1:
19
18
17
16
15
04
03
02
11
10
1/
1.
1-
1,
0+
0*
0)
0(
0'
0&
0%
0$
0#
0"
0!
$end
#10
1)
0C
1D
0B
1=
0?
1(
01
12
00
1+
0-
1$
#20
0)
1C
0D
1B
0=
1?
0(
11
02
10
0+
1-
1#
0$
#30
1)
0C
1D
0B
1=
0?
1(
01
12
00
1+
0-
1$
#40
0)
1C
0D
1B
0=
1?
1'
0(
0:
11
1;
02
09
10
14
0+
06
1-
1"
0#
0$
#50
1)
0C
1D
0B
1=
0?
1(
01
12
00
1+
0-
1$
#60
0)
1C
0D
1B
0=
1?
0(
11
02
10
0+
1-
1#
0$
#70
1)
0C
1D
0B
1=
0?
1(
01
12
00
1+
0-
1$
#80
0)
1C
0D
1B
0=
1?
0'
0(
1:
11
0;
02
19
10
04
0+
16
1-
1!
0"
0#
0$
#90
1)
0C
1D
0B
1=
0?
1(
01
12
00
1+
0-
1$
#100
0)
1C
0D
1B
0=
1?
0(
11
02
10
0+
1-
1#
0$
#110
1)
0C
1D
0B
1=
0?
1(
01
12
00
1+
0-
1$
#120
0)
1C
0D
1B
0=
1?
1'
0(
0:
11
1;
02
09
10
14
0+
06
1-
1"
0#
0$
#130
1)
0C
1D
0B
1=
0?
1(
01
12
00
1+
0-
1$
#140
0)
1C
0D
1B
0=
1?
0(
11
02
10
0+
1-
1#
0$
#150
1)
0C
1D
0B
1=
0?
1(
01
12
00
1+
0-
1$
#160
0)
1C
0D
1B
0=
1?
0'
0(
1:
11
0;
02
19
10
04
0+
16
1-
0,
05
0!
0"
0#
0$
1&
#170
1$
#180
1)
0C
1D
0B
1=
0?
1(
01
12
0/
1*
0.
1#
0$
#190
1$
#200
0)
1C
0D
1B
0=
1?
0(
11
02
1/
0*
1.
1"
0#
0$
#210
1$
#220
1)
0C
1D
0B
1=
0?
1(
01
12
0/
1*
0.
1#
0$
#230
1$
#240
0)
1C
0D
1B
0=
1?
1'
0(
0:
11
1;
02
08
1/
13
0*
07
1.
1!
0"
0#
0$
#250
1$
#260
1)
0C
1D
0B
1=
0?
1(
01
12
0/
1*
0.
1#
0$
#270
1$
#280
0)
1C
0D
1B
0=
1?
0(
11
02
1/
0*
1.
1"
0#
0$
#290
1$
#300
1)
0C
1D
0B
1=
0?
1(
01
12
0/
1*
0.
1#
0$
#310
1$
#320
0)
1C
0D
0(
0'
11
1:
1B
02
0;
0=
1A
1/
18
1?
0<
0*
03
0>
1@
1,
1.
15
17
0!
0"
0#
0$
1%
0&
#330
1(
01
12
00
1+
0-
1$
#340
0(
11
02
10
0+
1-
1#
0$
#350
1(
01
12
00
1+
0-
1$
#360
1)
0C
1D
0A
1<
0@
1'
0(
0:
11
1;
02
09
10
14
0+
06
1-
1"
0#
0$
#370
1(
01
12
00
1+
0-
1$
#380
0(
11
02
10
0+
1-
1#
0$
#390
1(
01
12
00
1+
0-
1$
#400
0)
1C
0D
1A
0<
1@
0'
0(
1:
11
0;
02
19
10
04
0+
16
1-
1!
0"
0#
0$
#410
1(
01
12
00
1+
0-
1$
#420
0(
11
02
10
0+
1-
1#
0$
#430
1(
01
12
00
1+
0-
1$
#440
1)
0C
1D
0A
1<
0@
1'
0(
0:
11
1;
02
09
10
14
0+
06
1-
1"
0#
0$
#450
1(
01
12
00
1+
0-
1$
#460
0(
11
02
10
0+
1-
1#
0$
#470
1(
01
12
00
1+
0-
1$
#480
0)
1C
0D
1A
0<
1@
0'
0(
1:
11
0;
02
19
10
04
0+
16
1-
0,
05
0!
0"
0#
0$
1&
#490
1$
#500
1(
01
12
0/
1*
0.
1#
0$
#510
1$
#520
0(
11
02
1/
0*
1.
1"
0#
0$
#530
1$
#540
1(
01
12
0/
1*
0.
1#
0$
#550
1$
#560
1)
0C
1D
0A
1<
0@
1'
0(
0:
11
1;
02
08
1/
13
0*
07
1.
1!
0"
0#
0$
#570
1$
#580
1(
01
12
0/
1*
0.
1#
0$
#590
1$
#600
0(
11
02
1/
0*
1.
1"
0#
0$
#610
1$
#620
1(
01
12
0/
1*
0.
1#
0$
#630
1$
